[
    {
        "account": 1,
        "username": "Ryan",
        "salt": "skVJ31MuWqvmuIRE",
        "password": "33f2e27f5f982ec097ea528716ccc418bbf4b8a11786ea03672cffacee29331c",
        "attempts": 0,
        "session": ""
    },
    {
        "account": 2,
        "firstname": "Ry",
        "lastname": "Ku",
        "username": "ryry",
        "salt": "MCeERR1mjDqxwGtK",
        "password": "63495c3b4fdf9c4d688d6186eaf6e5d2bdd45e625beb6cc9d99c6a9d7cce2fad",
        "attempts": 0,
        "session": ""
    }
]